codecombat/__init__.py
codecombat/client.py
codecombat/core/__init__.py
codecombat/core/api_error.py
codecombat/core/client_wrapper.py
codecombat/core/datetime_utils.py
codecombat/core/jsonable_encoder.py
codecombat/core/remove_none_from_dict.py
codecombat/environment.py
codecombat/py.typed
codecombat/resources/__init__.py
codecombat/resources/auth/__init__.py
codecombat/resources/auth/client.py
codecombat/resources/clans/__init__.py
codecombat/resources/clans/client.py
codecombat/resources/classrooms/__init__.py
codecombat/resources/classrooms/client.py
codecombat/resources/stats/__init__.py
codecombat/resources/stats/client.py
codecombat/resources/users/__init__.py
codecombat/resources/users/client.py
codecombat/types/__init__.py
codecombat/types/clan_response.py
codecombat/types/classroom_response.py
codecombat/types/classroom_response_courses_item.py
codecombat/types/classroom_response_with_code.py
codecombat/types/classroom_response_with_code_courses_item.py
codecombat/types/classrooms_create_request_ace_config.py
codecombat/types/classrooms_get_members_stats_response_item.py
codecombat/types/classrooms_get_members_stats_response_item_stats.py
codecombat/types/datetime_string.py
codecombat/types/level_session_response.py
codecombat/types/level_session_response_level.py
codecombat/types/level_session_response_state.py
codecombat/types/license_stats_response.py
codecombat/types/object_id_string.py
codecombat/types/playtime_stats_response.py
codecombat/types/role_string.py
codecombat/types/user_response.py
codecombat/types/user_response_license.py
codecombat/types/user_response_o_auth_identities_item.py
codecombat/types/user_response_stats.py
codecombat/types/user_response_subscription.py
codecombat/types/users_create_request_hero_config.py
codecombat/types/users_create_request_role.py
codecombat-0.1.8.dist-info/METADATA
codecombat-0.1.8.dist-info/WHEEL
codecombat-0.1.8.dist-info/RECORD
